cb_kafka_consumer/__init__.py
cb_kafka_consumer/src/consumer.py
cb_kafka_consumer-0.1.6.dist-info/LICENSE
cb_kafka_consumer-0.1.6.dist-info/METADATA
cb_kafka_consumer-0.1.6.dist-info/WHEEL
cb_kafka_consumer-0.1.6.dist-info/top_level.txt
cb_kafka_consumer-0.1.6.dist-info/RECORD
