Metadata-Version: 2.1
Name: cb-kafka-consumer
Version: 0.1.6
Summary: A small example package
Author-email: Mehdi Bakhtiari <mehdone@gmail.com>
Classifier: Programming Language :: Python :: 3
Classifier: License :: OSI Approved :: MIT License
Classifier: Operating System :: OS Independent
Requires-Python: >=3.10
License-File: LICENSE
Requires-Dist: kafka-python (~=2.0.2)
Requires-Dist: python-snappy (~=0.6.1)
Requires-Dist: crc32c (~=2.3)
